pyproxy/__init__.py
pyproxy/utils/__init__.py
pyproxy/utils/decorators.py
pyproxy/utils/logger.py
pyproxy/utils/message.py
pyproxy/utils/protocols_manager.py
pyproxy/utils/websocket.py
py_ws_libp2p_proxy-0.3.2.dist-info/METADATA
py_ws_libp2p_proxy-0.3.2.dist-info/WHEEL
py_ws_libp2p_proxy-0.3.2.dist-info/licenses/LICENSE
py_ws_libp2p_proxy-0.3.2.dist-info/RECORD
