Metadata-Version: 2.4
Name: py-ws-libp2p-proxy
Version: 0.3.2
Summary: API for libp2p-ws-proxy
License: Apache-2.0
License-File: LICENSE
Author: Mariia Livshits
Author-email: m.bystramovich@gmail.com
Requires-Python: >=3.9,<4.0
Classifier: License :: OSI Approved :: Apache Software License
Classifier: Programming Language :: Python :: 3
Classifier: Programming Language :: Python :: 3.9
Classifier: Programming Language :: Python :: 3.10
Classifier: Programming Language :: Python :: 3.11
Classifier: Programming Language :: Python :: 3.12
Classifier: Programming Language :: Python :: 3.13
Classifier: Programming Language :: Python :: 3.14
Requires-Dist: websockets (>=15.0.0)
Project-URL: Repository, https://github.com/tubleronchik/py-libp2p-proxy
